[
  {
    "file": "tezt/self_tests/test_michelson_script.ml",
    "title": "michelson_scripts: version_range7",
    "tags": [
      "michelson_scripts",
      "version_range"
    ],
    "successful_runs": {
      "total_time": "34147",
      "count": "1"
    }
  },
  {
    "file": "tezt/self_tests/test_daemon.ml",
    "title": "Daemon.nth_event calls should independent",
    "tags": [
      "daemon",
      "nth_event"
    ],
    "successful_runs": {
      "total_time": "308",
      "count": "1"
    }
  },
  {
    "file": "src/proto_alpha/lib_protocol/test/unit/test_sc_rollup_storage.ml",
    "title": "alpha: sc rollup storage (withdraw twice fails)",
    "tags": [
      "alcotezt",
      "quick",
      "alpha"
    ],
    "successful_runs": {
      "total_time": "23857",
      "count": "1"
    }
  },
  {
    "file": "src/proto_alpha/lib_protocol/test/unit/test_sc_rollup_storage.ml",
    "title": "alpha: sc rollup storage (conflict_point_computation_fits_in_gas_limit)",
    "tags": [
      "alcotezt",
      "quick",
      "alpha"
    ],
    "successful_runs": {
      "total_time": "755153",
      "count": "1"
    }
  },
  {
    "file": "src/proto_alpha/lib_protocol/test/unit/test_sc_rollup_inbox.ml",
    "title": "alpha: sc rollup inbox (messages are correctly added in payloads history)",
    "tags": [
      "alcotezt",
      "slow",
      "alpha"
    ],
    "successful_runs": {
      "total_time": "335444",
      "count": "1"
    }
  },
  {
    "file": "src/proto_alpha/lib_protocol/test/unit/test_liquidity_baking_repr.ml",
    "title": "alpha: liquidity baking (voting On and Off have symmetric effects on the EMA)",
    "tags": [
      "alcotezt",
      "quick",
      "alpha"
    ],
    "successful_runs": {
      "total_time": "486",
      "count": "1"
    }
  },
  {
    "file": "src/proto_alpha/lib_protocol/test/unit/test_global_constants_storage.ml",
    "title": "alpha: Global constants storage (expand: data)",
    "tags": [
      "alcotezt",
      "quick",
      "alpha"
    ],
    "successful_runs": {
      "total_time": "18448",
      "count": "1"
    }
  },
  {
    "file": "src/proto_alpha/lib_protocol/test/unit/test_dal_slot_proof.ml",
    "title": "alpha: dal slot proof ([test] Confirmed slot on top of genesis: unconfirmed page with bad data (altered))",
    "tags": [
      "alcotezt",
      "quick",
      "alpha"
    ],
    "successful_runs": {
      "total_time": "599582",
      "count": "1"
    }
  },
  {
    "file": "src/proto_alpha/lib_protocol/test/regression/test_logging.ml",
    "title": "alpha: check_signature",
    "tags": [
      "regression",
      "protocol",
      "regression",
      "logging"
    ],
    "successful_runs": {
      "total_time": "32138",
      "count": "1"
    }
  },
  {
    "file": "src/proto_alpha/lib_protocol/test/regression/test_logging.ml",
    "title": "alpha: set_delegate",
    "tags": [
      "regression",
      "protocol",
      "regression",
      "logging"
    ],
    "successful_runs": {
      "total_time": "19532",
      "count": "1"
    }
  },
  {
    "file": "src/proto_alpha/lib_protocol/test/pbt/test_zk_rollup_encoding.ml",
    "title": "alpha: ZK rollup encoding: : roundtrip (roundtrip Zk_rollup_operation_repr.t)",
    "tags": [
      "alcotezt",
      "slow",
      "alpha"
    ],
    "successful_runs": {
      "total_time": "1761450",
      "count": "1"
    }
  },
  {
    "file": "src/proto_alpha/lib_protocol/test/pbt/test_refutation_game.ml",
    "title": "alpha: Refutation_game: Refutation (Perfect against Random)",
    "tags": [
      "alcotezt",
      "slow",
      "alpha"
    ],
    "successful_runs": {
      "total_time": "30508069",
      "count": "1"
    }
  },
  {
    "file": "src/proto_alpha/lib_protocol/test/pbt/test_carbonated_map.ml",
    "title": "alpha: Carbonated map (Merge overlap replace)",
    "tags": [
      "alcotezt",
      "quick",
      "alpha"
    ],
    "successful_runs": {
      "total_time": "10998",
      "count": "1"
    }
  },
  {
    "file": "src/proto_alpha/lib_protocol/test/pbt/saturation_fuzzing.ml",
    "title": "alpha: sub (t - t = 0)",
    "tags": [
      "alcotezt",
      "slow",
      "alpha"
    ],
    "successful_runs": {
      "total_time": "263",
      "count": "1"
    }
  },
  {
    "file": "src/proto_alpha/lib_protocol/test/integration/operations/test_voting.ml",
    "title": "alpha: voting (voting proposal, no winning proposal)",
    "tags": [
      "alcotezt",
      "quick",
      "alpha"
    ],
    "successful_runs": {
      "total_time": "604130",
      "count": "1"
    }
  },
  {
    "file": "src/proto_alpha/lib_protocol/test/integration/operations/test_transfer.ml",
    "title": "alpha: transfer (balance too low with two transfers - transfer zero)",
    "tags": [
      "alcotezt",
      "quick",
      "alpha"
    ],
    "successful_runs": {
      "total_time": "11161",
      "count": "1"
    }
  },
  {
    "file": "src/proto_alpha/lib_protocol/test/integration/operations/test_sc_rollup.ml",
    "title": "alpha: sc rollup (insufficient ticket balances)",
    "tags": [
      "alcotezt",
      "quick",
      "alpha"
    ],
    "successful_runs": {
      "total_time": "137897",
      "count": "1"
    }
  },
  {
    "file": "src/proto_alpha/lib_protocol/test/integration/operations/test_reveal.ml",
    "title": "alpha: revelation (cannot batch a good reveal after one emptying account)",
    "tags": [
      "alcotezt",
      "quick",
      "alpha"
    ],
    "successful_runs": {
      "total_time": "9872",
      "count": "1"
    }
  },
  {
    "file": "src/proto_alpha/lib_protocol/test/integration/operations/test_activation.ml",
    "title": "alpha: activation (multi-activation one-by-one)",
    "tags": [
      "alcotezt",
      "quick",
      "alpha"
    ],
    "successful_runs": {
      "total_time": "83880",
      "count": "1"
    }
  },
  {
    "file": "src/proto_alpha/lib_protocol/test/integration/michelson/test_typechecking.ml",
    "title": "alpha: typechecking (lambda_rec instruction with apply)",
    "tags": [
      "alcotezt",
      "quick",
      "alpha"
    ],
    "successful_runs": {
      "total_time": "10421",
      "count": "1"
    }
  },
  {
    "file": "src/proto_alpha/lib_protocol/test/integration/michelson/test_ticket_scanner.ml",
    "title": "alpha: ticket scanner (tickets in map with zero amount)",
    "tags": [
      "alcotezt",
      "quick",
      "alpha"
    ],
    "successful_runs": {
      "total_time": "8562",
      "count": "1"
    }
  },
  {
    "file": "src/proto_alpha/lib_protocol/test/integration/michelson/test_ticket_lazy_storage_diff.ml",
    "title": "alpha: ticket lazy storage diff (copy with multiple updates to same key)",
    "tags": [
      "alcotezt",
      "quick",
      "alpha"
    ],
    "successful_runs": {
      "total_time": "10010",
      "count": "1"
    }
  },
  {
    "file": "src/proto_alpha/lib_protocol/test/integration/michelson/test_ticket_accounting.ml",
    "title": "alpha: ticket accounting (ticket-token map with duplicate keys)",
    "tags": [
      "alcotezt",
      "quick",
      "alpha"
    ],
    "successful_runs": {
      "total_time": "10403",
      "count": "1"
    }
  },
  {
    "file": "src/proto_alpha/lib_protocol/test/integration/michelson/test_sapling.ml",
    "title": "alpha: sapling (shielded_tez)",
    "tags": [
      "alcotezt",
      "quick",
      "alpha"
    ],
    "successful_runs": {
      "total_time": "329974226",
      "count": "1"
    }
  },
  {
    "file": "src/proto_alpha/lib_protocol/test/integration/michelson/test_lambda_normalization.ml",
    "title": "alpha: lambda normalization (lambdas are normalized to optimized format during elaboration)",
    "tags": [
      "alcotezt",
      "quick",
      "alpha"
    ],
    "successful_runs": {
      "total_time": "483923",
      "count": "1"
    }
  },
  {
    "file": "src/proto_alpha/lib_protocol/test/integration/gas/test_gas_levels.ml",
    "title": "alpha: gas levels (both lists and single operations with contract nil)",
    "tags": [
      "alcotezt",
      "quick",
      "alpha"
    ],
    "successful_runs": {
      "total_time": "19850",
      "count": "1"
    }
  },
  {
    "file": "src/proto_alpha/lib_protocol/test/integration/consensus/test_preendorsement.ml",
    "title": "alpha: preendorsement (AppMode: ko: preendorsement_has_wrong_level)",
    "tags": [
      "alcotezt",
      "quick",
      "alpha"
    ],
    "successful_runs": {
      "total_time": "22298",
      "count": "1"
    }
  },
  {
    "file": "src/proto_alpha/lib_protocol/test/integration/consensus/test_endorsement.ml",
    "title": "alpha: endorsement (Fitness gap)",
    "tags": [
      "alcotezt",
      "quick",
      "alpha"
    ],
    "successful_runs": {
      "total_time": "37441",
      "count": "1"
    }
  },
  {
    "file": "src/proto_alpha/lib_protocol/test/integration/consensus/test_double_baking.ml",
    "title": "alpha: double baking (same blocks)",
    "tags": [
      "alcotezt",
      "quick",
      "alpha"
    ],
    "successful_runs": {
      "total_time": "33123",
      "count": "1"
    }
  },
  {
    "file": "src/proto_alpha/lib_protocol/test/integration/consensus/test_delegation.ml",
    "title": "alpha: delegation (registered and revealed self-delegation)",
    "tags": [
      "alcotezt",
      "quick",
      "alpha"
    ],
    "successful_runs": {
      "total_time": "38400",
      "count": "1"
    }
  },
  {
    "file": "src/proto_alpha/lib_protocol/test/integration/test_frozen_bonds.ml",
    "title": "alpha: frozen bonds (frozen bonds - delegate then freeze)",
    "tags": [
      "alcotezt",
      "quick",
      "alpha"
    ],
    "successful_runs": {
      "total_time": "9996",
      "count": "1"
    }
  },
  {
    "file": "src/proto_alpha/lib_delegate/test/test_scenario.ml",
    "title": "mockup_baking: alpha: scenario m3 (alpha: scenario m3)",
    "tags": [
      "alcotezt",
      "quick",
      "alpha"
    ],
    "successful_runs": {
      "total_time": "26911174",
      "count": "1"
    }
  },
  {
    "file": "src/proto_alpha/lib_client/test/test_michelson_v1_macros.ml",
    "title": "alpha: micheline v1 macros (unpair expansion)",
    "tags": [
      "alcotezt",
      "quick",
      "alpha"
    ],
    "successful_runs": {
      "total_time": "234",
      "count": "1"
    }
  },
  {
    "file": "src/proto_alpha/lib_client/test/test_michelson_v1_macros.ml",
    "title": "alpha: micheline v1 macros (assert_right unexpansion)",
    "tags": [
      "alcotezt",
      "quick",
      "alpha"
    ],
    "successful_runs": {
      "total_time": "231",
      "count": "1"
    }
  },
  {
    "file": "src/proto_017_PtNairob/lib_sc_rollup_node/test/canary.ml",
    "title": "canary: 017-PtNairob: canary (canary arith)",
    "tags": [
      "alcotezt",
      "quick",
      "nairobi"
    ],
    "successful_runs": {
      "total_time": "185097",
      "count": "1"
    }
  },
  {
    "file": "src/proto_017_PtNairob/lib_protocol/test/unit/test_tez_repr.ml",
    "title": "017-PtNairob: Tez_repr.ml (Tez.of_mutez: of negative ints)",
    "tags": [
      "alcotezt",
      "quick",
      "nairobi"
    ],
    "successful_runs": {
      "total_time": "313",
      "count": "1"
    }
  },
  {
    "file": "src/proto_017_PtNairob/lib_protocol/test/unit/test_sc_rollup_storage.ml",
    "title": "017-PtNairob: sc rollup storage (deposit then withdraw)",
    "tags": [
      "alcotezt",
      "quick",
      "nairobi"
    ],
    "successful_runs": {
      "total_time": "16376",
      "count": "1"
    }
  },
  {
    "file": "src/proto_017_PtNairob/lib_protocol/test/unit/test_sc_rollup_storage.ml",
    "title": "017-PtNairob: sc rollup storage (withdraw when staked before or at LCC)",
    "tags": [
      "alcotezt",
      "quick",
      "nairobi"
    ],
    "successful_runs": {
      "total_time": "42423",
      "count": "1"
    }
  },
  {
    "file": "src/proto_017_PtNairob/lib_protocol/test/unit/test_sc_rollup_inbox.ml",
    "title": "017-PtNairob: sc rollup inbox (negative test of inclusion proof.)",
    "tags": [
      "alcotezt",
      "slow",
      "nairobi"
    ],
    "successful_runs": {
      "total_time": "3322937",
      "count": "1"
    }
  },
  {
    "file": "src/proto_017_PtNairob/lib_protocol/test/unit/test_operation_repr.ml",
    "title": "017-PtNairob: Operation_repr.ml (protocol_data_encoding: multiple non manager)",
    "tags": [
      "alcotezt",
      "quick",
      "nairobi"
    ],
    "successful_runs": {
      "total_time": "1739",
      "count": "1"
    }
  },
  {
    "file": "src/proto_017_PtNairob/lib_protocol/test/regression/test_logging.ml",
    "title": "017_PtNairob: rec_id_unit",
    "tags": [
      "regression",
      "protocol",
      "regression",
      "logging"
    ],
    "successful_runs": {
      "total_time": "27041",
      "count": "1"
    }
  },
  {
    "file": "src/proto_017_PtNairob/lib_protocol/test/pbt/test_dal_slot_proof.ml",
    "title": "017-PtNairob: Dal slots refutation game: [017-PtNairob: test] Dal slots refutation (Pbt tests: unconfirmed pages)",
    "tags": [
      "alcotezt",
      "slow",
      "nairobi"
    ],
    "successful_runs": {
      "total_time": "15348287",
      "count": "1"
    }
  },
  {
    "file": "src/proto_017_PtNairob/lib_protocol/test/integration/validate/test_validation_batch.ml",
    "title": "017-PtNairob: batched managers validation (reveal in the middle)",
    "tags": [
      "alcotezt",
      "quick",
      "nairobi"
    ],
    "successful_runs": {
      "total_time": "8313324",
      "count": "1"
    }
  },
  {
    "file": "src/proto_017_PtNairob/lib_protocol/test/integration/validate/test_manager_operation_validation.ml",
    "title": "017-PtNairob: single manager validation (dal disabled)",
    "tags": [
      "alcotezt",
      "quick",
      "nairobi"
    ],
    "successful_runs": {
      "total_time": "1932516",
      "count": "1"
    }
  },
  {
    "file": "src/proto_017_PtNairob/lib_protocol/test/integration/validate/test_covalidity.ml",
    "title": "017-PtNairob: covalidity (scenario: 'exploration' period, 'vdf' seed)",
    "tags": [
      "alcotezt",
      "slow",
      "nairobi"
    ],
    "successful_runs": {
      "total_time": "6648059",
      "count": "1"
    }
  },
  {
    "file": "src/proto_017_PtNairob/lib_protocol/test/integration/operations/test_zk_rollup.ml",
    "title": "017-PtNairob: zk rollup (update with false proof)",
    "tags": [
      "alcotezt",
      "quick",
      "nairobi"
    ],
    "successful_runs": {
      "total_time": "3911589",
      "count": "1"
    }
  },
  {
    "file": "src/proto_017_PtNairob/lib_protocol/test/integration/operations/test_voting.ml",
    "title": "017-PtNairob: voting (Ballot source not in vote listings)",
    "tags": [
      "alcotezt",
      "quick",
      "nairobi"
    ],
    "successful_runs": {
      "total_time": "33253",
      "count": "1"
    }
  },
  {
    "file": "src/proto_017_PtNairob/lib_protocol/test/integration/operations/test_transfer.ml",
    "title": "017-PtNairob: transfer (random transfer)",
    "tags": [
      "alcotezt",
      "quick",
      "nairobi"
    ],
    "successful_runs": {
      "total_time": "27730",
      "count": "1"
    }
  },
  {
    "file": "src/proto_017_PtNairob/lib_protocol/test/integration/operations/test_sc_rollup.ml",
    "title": "017-PtNairob: sc rollup (originating with proof for Tezos context trees trying to pass as a binary tree)",
    "tags": [
      "alcotezt",
      "quick",
      "nairobi"
    ],
    "successful_runs": {
      "total_time": "17702",
      "count": "1"
    }
  },
  {
    "file": "src/proto_017_PtNairob/lib_protocol/test/integration/operations/test_reveal.ml",
    "title": "017-PtNairob: revelation (do not reveal when gas exhausted)",
    "tags": [
      "alcotezt",
      "quick",
      "nairobi"
    ],
    "successful_runs": {
      "total_time": "23629",
      "count": "1"
    }
  },
  {
    "file": "src/proto_017_PtNairob/lib_protocol/test/integration/michelson/test_ticket_storage.ml",
    "title": "017-PtNairob: ticket storage (empty balance after update)",
    "tags": [
      "alcotezt",
      "quick",
      "nairobi"
    ],
    "successful_runs": {
      "total_time": "40663",
      "count": "1"
    }
  },
  {
    "file": "src/proto_017_PtNairob/lib_protocol/test/integration/michelson/test_ticket_manager.ml",
    "title": "017-PtNairob: ticket manager (Mix of operations)",
    "tags": [
      "alcotezt",
      "quick",
      "nairobi"
    ],
    "successful_runs": {
      "total_time": "122656",
      "count": "1"
    }
  },
  {
    "file": "src/proto_017_PtNairob/lib_protocol/test/integration/michelson/test_ticket_balance.ml",
    "title": "017-PtNairob: ticket balance (storage for create and remove tickets)",
    "tags": [
      "alcotezt",
      "quick",
      "nairobi"
    ],
    "successful_runs": {
      "total_time": "136685",
      "count": "1"
    }
  },
  {
    "file": "src/proto_017_PtNairob/lib_protocol/test/integration/michelson/test_temp_big_maps.ml",
    "title": "017-PtNairob: temp big maps (temp_big_maps(Left False, 2))",
    "tags": [
      "alcotezt",
      "quick",
      "nairobi"
    ],
    "successful_runs": {
      "total_time": "35822",
      "count": "1"
    }
  },
  {
    "file": "src/proto_017_PtNairob/lib_protocol/test/integration/michelson/test_sapling.ml",
    "title": "017-PtNairob: sapling (verifyupdate_two_transactions)",
    "tags": [
      "alcotezt",
      "quick",
      "nairobi"
    ],
    "successful_runs": {
      "total_time": "21651846",
      "count": "1"
    }
  },
  {
    "file": "src/proto_017_PtNairob/lib_protocol/test/integration/michelson/test_interpretation.ml",
    "title": "017-PtNairob: interpretation (test error encoding: Overflow)",
    "tags": [
      "alcotezt",
      "quick",
      "nairobi"
    ],
    "successful_runs": {
      "total_time": "12186",
      "count": "1"
    }
  },
  {
    "file": "src/proto_017_PtNairob/lib_protocol/test/integration/gas/test_gas_levels.ml",
    "title": "017-PtNairob: gas levels (bake one operation list with contract nil)",
    "tags": [
      "alcotezt",
      "quick",
      "nairobi"
    ],
    "successful_runs": {
      "total_time": "33951",
      "count": "1"
    }
  },
  {
    "file": "src/proto_017_PtNairob/lib_protocol/test/integration/consensus/test_preendorsement.ml",
    "title": "017-PtNairob: preendorsement (AppMode: ko:locked_round_not_before_block_round)",
    "tags": [
      "alcotezt",
      "quick",
      "nairobi"
    ],
    "successful_runs": {
      "total_time": "22439",
      "count": "1"
    }
  },
  {
    "file": "src/proto_017_PtNairob/lib_protocol/test/integration/consensus/test_double_preendorsement.ml",
    "title": "017-PtNairob: double preendorsement (ConstrMode: ko: malformed_double_preendorsement_denunciation_different_validators)",
    "tags": [
      "alcotezt",
      "quick",
      "nairobi"
    ],
    "successful_runs": {
      "total_time": "41018",
      "count": "1"
    }
  },
  {
    "file": "src/proto_017_PtNairob/lib_protocol/test/integration/consensus/test_delegation.ml",
    "title": "017-PtNairob: delegation (contracts not registered as delegate can change their delegation (max fee))",
    "tags": [
      "alcotezt",
      "quick",
      "nairobi"
    ],
    "successful_runs": {
      "total_time": "20934",
      "count": "1"
    }
  },
  {
    "file": "src/proto_017_PtNairob/lib_protocol/test/integration/consensus/test_delegation.ml",
    "title": "017-PtNairob: delegation (valid delegate registration: credit 1μꜩ, self delegation, debit 1μꜩ (init with delegation))",
    "tags": [
      "alcotezt",
      "quick",
      "nairobi"
    ],
    "successful_runs": {
      "total_time": "25426",
      "count": "1"
    }
  },
  {
    "file": "src/proto_017_PtNairob/lib_protocol/test/integration/test_liquidity_baking.ml",
    "title": "017-PtNairob: liquidity baking (liquidity baking toggle vote with 80% of bakers voting LB_off baking 100 blocks longer)",
    "tags": [
      "alcotezt",
      "quick",
      "nairobi"
    ],
    "successful_runs": {
      "total_time": "2593822",
      "count": "1"
    }
  },
  {
    "file": "src/proto_017_PtNairob/lib_protocol/test/integration/test_frozen_bonds.ml",
    "title": "017-PtNairob: frozen bonds (delegate, freeze, redelegate, unfreeze)",
    "tags": [
      "alcotezt",
      "quick",
      "nairobi"
    ],
    "successful_runs": {
      "total_time": "9834",
      "count": "1"
    }
  },
  {
    "file": "src/proto_017_PtNairob/lib_plugin/test/test_conflict_handler.ml",
    "title": "017-PtNairob/plugin: conflict_handler: non-manager operations",
    "tags": [
      "nairobi",
      "plugin",
      "mempool",
      "conflict_handler",
      "nonmanager",
      "random"
    ],
    "successful_runs": {
      "total_time": "1304833",
      "count": "1"
    }
  },
  {
    "file": "src/proto_017_PtNairob/lib_dal/test/test_dal_slot_frame_encoding.ml",
    "title": "017-PtNairob: [Unit] Slot_framing_protocol.ml (Encoded slot can be decoded (V0, 1 rollup))",
    "tags": [
      "alcotezt",
      "quick",
      "nairobi"
    ],
    "successful_runs": {
      "total_time": "203",
      "count": "1"
    }
  },
  {
    "file": "src/proto_017_PtNairob/lib_client/test/test_michelson_v1_macros.ml",
    "title": "017-PtNairob: micheline v1 macros (assert_right annot unexpansion)",
    "tags": [
      "alcotezt",
      "quick",
      "nairobi"
    ],
    "successful_runs": {
      "total_time": "277",
      "count": "1"
    }
  },
  {
    "file": "src/proto_017_PtNairob/lib_client/test/test_michelson_v1_macros.ml",
    "title": "017-PtNairob: micheline v1 macros (set_cdr unexpansion)",
    "tags": [
      "alcotezt",
      "quick",
      "nairobi"
    ],
    "successful_runs": {
      "total_time": "185",
      "count": "1"
    }
  },
  {
    "file": "src/proto_016_PtMumbai/lib_protocol/test/unit/test_zk_rollup_storage.ml",
    "title": "016-PtMumbai: zk rollup storage (pending_list_append errors)",
    "tags": [
      "alcotezt",
      "quick",
      "mumbai"
    ],
    "successful_runs": {
      "total_time": "3549072",
      "count": "1"
    }
  },
  {
    "file": "src/proto_016_PtMumbai/lib_protocol/test/unit/test_tx_rollup_l2_apply.ml",
    "title": "016-PtMumbai: tx rollup l2 apply (simple l2 transaction)",
    "tags": [
      "alcotezt",
      "quick",
      "mumbai"
    ],
    "successful_runs": {
      "total_time": "21717",
      "count": "1"
    }
  },
  {
    "file": "src/proto_016_PtMumbai/lib_protocol/test/unit/test_tx_rollup_l2.ml",
    "title": "016-PtMumbai: tx rollup l2 (Address, test the limit of indexes)",
    "tags": [
      "alcotezt",
      "quick",
      "mumbai"
    ],
    "successful_runs": {
      "total_time": "7154",
      "count": "1"
    }
  },
  {
    "file": "src/proto_016_PtMumbai/lib_protocol/test/unit/test_skip_list_repr.ml",
    "title": "016-PtMumbai: skip list (Skip list: `search` may not produce minimal path)",
    "tags": [
      "alcotezt",
      "slow",
      "mumbai"
    ],
    "successful_runs": {
      "total_time": "1631",
      "count": "1"
    }
  },
  {
    "file": "src/proto_016_PtMumbai/lib_protocol/test/unit/test_sc_rollup_storage.ml",
    "title": "016-PtMumbai: sc rollup storage (last cemented commitment hash and level returns correct information)",
    "tags": [
      "alcotezt",
      "quick",
      "mumbai"
    ],
    "successful_runs": {
      "total_time": "29577",
      "count": "1"
    }
  },
  {
    "file": "src/proto_016_PtMumbai/lib_protocol/test/unit/test_sc_rollup_storage.ml",
    "title": "016-PtMumbai: sc rollup storage (Getting cemented commitments with levels of missing rollups fails)",
    "tags": [
      "alcotezt",
      "quick",
      "mumbai"
    ],
    "successful_runs": {
      "total_time": "37963",
      "count": "1"
    }
  },
  {
    "file": "src/proto_016_PtMumbai/lib_protocol/test/unit/test_saturation.ml",
    "title": "016-PtMumbai: saturation arithmetic (Square root)",
    "tags": [
      "alcotezt",
      "quick",
      "mumbai"
    ],
    "successful_runs": {
      "total_time": "179",
      "count": "1"
    }
  },
  {
    "file": "src/proto_016_PtMumbai/lib_protocol/test/unit/test_round_repr.ml",
    "title": "016-PtMumbai: round (level_offset_of_round)",
    "tags": [
      "alcotezt",
      "quick",
      "mumbai"
    ],
    "successful_runs": {
      "total_time": "153",
      "count": "1"
    }
  },
  {
    "file": "src/proto_016_PtMumbai/lib_protocol/test/unit/test_liquidity_baking_repr.ml",
    "title": "016-PtMumbai: liquidity baking (EMA decreases when vote is On)",
    "tags": [
      "alcotezt",
      "quick",
      "mumbai"
    ],
    "successful_runs": {
      "total_time": "161",
      "count": "1"
    }
  },
  {
    "file": "src/proto_016_PtMumbai/lib_protocol/test/unit/test_destination_repr.ml",
    "title": "016-PtMumbai: Destination_repr.ml (Comparison of destinations)",
    "tags": [
      "alcotezt",
      "quick",
      "mumbai"
    ],
    "successful_runs": {
      "total_time": "223",
      "count": "1"
    }
  },
  {
    "file": "src/proto_016_PtMumbai/lib_protocol/test/unit/test_dal_slot_proof.ml",
    "title": "016-PtMumbai: dal slot proof ([test] Confirmed slot on top of genesis: confirmed page with too long data)",
    "tags": [
      "alcotezt",
      "quick",
      "mumbai"
    ],
    "successful_runs": {
      "total_time": "1356850",
      "count": "1"
    }
  },
  {
    "file": "src/proto_016_PtMumbai/lib_protocol/test/pbt/test_sc_rollup_tick_repr.ml",
    "title": "016-PtMumbai: Tick_repr (distance from non-self is non-zero)",
    "tags": [
      "alcotezt",
      "slow",
      "mumbai"
    ],
    "successful_runs": {
      "total_time": "12520",
      "count": "1"
    }
  },
  {
    "file": "src/proto_016_PtMumbai/lib_protocol/test/pbt/test_refutation_game.ml",
    "title": "016-PtMumbai: Refutation_game: Dissection (distance < nb_of_sections => (len dissection = succ (dist dissection)))",
    "tags": [
      "alcotezt",
      "slow",
      "mumbai"
    ],
    "successful_runs": {
      "total_time": "31510",
      "count": "1"
    }
  },
  {
    "file": "src/proto_016_PtMumbai/lib_protocol/test/pbt/test_merkle_list.ml",
    "title": "016-PtMumbai: check_path (check_path)",
    "tags": [
      "alcotezt",
      "slow",
      "mumbai"
    ],
    "successful_runs": {
      "total_time": "14136849",
      "count": "1"
    }
  },
  {
    "file": "src/proto_016_PtMumbai/lib_protocol/test/pbt/test_carbonated_map.ml",
    "title": "016-PtMumbai: Carbonated map (Empty map is left identity for merge)",
    "tags": [
      "alcotezt",
      "slow",
      "mumbai"
    ],
    "successful_runs": {
      "total_time": "2294409",
      "count": "1"
    }
  },
  {
    "file": "src/proto_016_PtMumbai/lib_protocol/test/integration/validate/test_mempool.ml",
    "title": "016-PtMumbai: mempool (remove operations)",
    "tags": [
      "alcotezt",
      "quick",
      "mumbai"
    ],
    "successful_runs": {
      "total_time": "17822",
      "count": "1"
    }
  },
  {
    "file": "src/proto_016_PtMumbai/lib_protocol/test/integration/validate/test_1m_restriction.ml",
    "title": "016-PtMumbai: one-manager restriction (under 1M, co-valid ops commute)",
    "tags": [
      "alcotezt",
      "slow",
      "mumbai"
    ],
    "successful_runs": {
      "total_time": "83143031",
      "count": "1"
    }
  },
  {
    "file": "src/proto_016_PtMumbai/lib_protocol/test/integration/operations/test_voting.ml",
    "title": "016-PtMumbai: voting (Proposals source not in vote listings)",
    "tags": [
      "alcotezt",
      "quick",
      "mumbai"
    ],
    "successful_runs": {
      "total_time": "62125",
      "count": "1"
    }
  },
  {
    "file": "src/proto_016_PtMumbai/lib_protocol/test/integration/operations/test_tx_rollup.ml",
    "title": "016-PtMumbai: tx rollup (regression test empty_l2_context_hash)",
    "tags": [
      "alcotezt",
      "quick",
      "mumbai"
    ],
    "successful_runs": {
      "total_time": "8267",
      "count": "1"
    }
  },
  {
    "file": "src/proto_016_PtMumbai/lib_protocol/test/integration/operations/test_tx_rollup.ml",
    "title": "016-PtMumbai: tx rollup (Originating `comparable_type` fails w/ tx rollups disabled)",
    "tags": [
      "alcotezt",
      "quick",
      "mumbai"
    ],
    "successful_runs": {
      "total_time": "30931",
      "count": "1"
    }
  },
  {
    "file": "src/proto_016_PtMumbai/lib_protocol/test/integration/operations/test_sc_rollup.ml",
    "title": "016-PtMumbai: sc rollup (win refutation game by forfeit with draw)",
    "tags": [
      "alcotezt",
      "quick",
      "mumbai"
    ],
    "successful_runs": {
      "total_time": "200968",
      "count": "1"
    }
  },
  {
    "file": "src/proto_016_PtMumbai/lib_protocol/test/integration/operations/test_activation.ml",
    "title": "016-PtMumbai: activation (multi-activation all at a time)",
    "tags": [
      "alcotezt",
      "quick",
      "mumbai"
    ],
    "successful_runs": {
      "total_time": "211535",
      "count": "1"
    }
  },
  {
    "file": "src/proto_016_PtMumbai/lib_protocol/test/integration/michelson/test_ticket_operations_diff.ml",
    "title": "016-PtMumbai: ticket operations diff (transfer to non-ticket contract)",
    "tags": [
      "alcotezt",
      "quick",
      "mumbai"
    ],
    "successful_runs": {
      "total_time": "17268",
      "count": "1"
    }
  },
  {
    "file": "src/proto_016_PtMumbai/lib_protocol/test/integration/michelson/test_ticket_balance_key.ml",
    "title": "016-PtMumbai: ticket balance key (string address)",
    "tags": [
      "alcotezt",
      "quick",
      "mumbai"
    ],
    "successful_runs": {
      "total_time": "16223",
      "count": "1"
    }
  },
  {
    "file": "src/proto_016_PtMumbai/lib_protocol/test/integration/michelson/test_ticket_accounting.ml",
    "title": "016-PtMumbai: ticket accounting (Diffs for tickets in args and storage)",
    "tags": [
      "alcotezt",
      "quick",
      "mumbai"
    ],
    "successful_runs": {
      "total_time": "19607",
      "count": "1"
    }
  },
  {
    "file": "src/proto_016_PtMumbai/lib_protocol/test/integration/michelson/test_script_cache.ml",
    "title": "016-PtMumbai: script cache (entries correctly list contracts in order)",
    "tags": [
      "alcotezt",
      "quick",
      "mumbai"
    ],
    "successful_runs": {
      "total_time": "54658",
      "count": "1"
    }
  },
  {
    "file": "src/proto_016_PtMumbai/lib_protocol/test/integration/gas/test_gas_levels.ml",
    "title": "016-PtMumbai: gas levels (multiple single operations with contract infinite loop)",
    "tags": [
      "alcotezt",
      "quick",
      "mumbai"
    ],
    "successful_runs": {
      "total_time": "19164",
      "count": "1"
    }
  },
  {
    "file": "src/proto_016_PtMumbai/lib_protocol/test/integration/consensus/test_preendorsement.ml",
    "title": "016-PtMumbai: preendorsement (ConstrMode: ko: test_preendorsement_with_bad_branch)",
    "tags": [
      "alcotezt",
      "quick",
      "mumbai"
    ],
    "successful_runs": {
      "total_time": "28983",
      "count": "1"
    }
  },
  {
    "file": "src/proto_016_PtMumbai/lib_protocol/test/integration/consensus/test_endorsement.ml",
    "title": "016-PtMumbai: endorsement (Endorsement for grandparent)",
    "tags": [
      "alcotezt",
      "quick",
      "mumbai"
    ],
    "successful_runs": {
      "total_time": "18613",
      "count": "1"
    }
  },
  {
    "file": "src/proto_016_PtMumbai/lib_protocol/test/integration/consensus/test_double_baking.ml",
    "title": "016-PtMumbai: double baking (same blocks)",
    "tags": [
      "alcotezt",
      "quick",
      "mumbai"
    ],
    "successful_runs": {
      "total_time": "22146",
      "count": "1"
    }
  },
  {
    "file": "src/proto_016_PtMumbai/lib_protocol/test/integration/consensus/test_delegation.ml",
    "title": "016-PtMumbai: delegation (originated bootstrap contract can be delegated)",
    "tags": [
      "alcotezt",
      "quick",
      "mumbai"
    ],
    "successful_runs": {
      "total_time": "16343",
      "count": "1"
    }
  },
  {
    "file": "src/proto_016_PtMumbai/lib_protocol/test/integration/test_token.ml",
    "title": "016-PtMumbai: token movements (transfer - test from empty sources to a destination)",
    "tags": [
      "alcotezt",
      "quick",
      "mumbai"
    ],
    "successful_runs": {
      "total_time": "10008",
      "count": "1"
    }
  },
  {
    "file": "src/proto_016_PtMumbai/lib_protocol/test/integration/test_frozen_bonds.ml",
    "title": "016-PtMumbai: frozen bonds (frozen bonds - test rpcs)",
    "tags": [
      "alcotezt",
      "quick",
      "mumbai"
    ],
    "successful_runs": {
      "total_time": "9396",
      "count": "1"
    }
  },
  {
    "file": "src/proto_016_PtMumbai/lib_client/test/test_michelson_v1_macros.ml",
    "title": "016-PtMumbai: micheline v1 macros (diip expansion)",
    "tags": [
      "alcotezt",
      "quick",
      "mumbai"
    ],
    "successful_runs": {
      "total_time": "216",
      "count": "1"
    }
  },
  {
    "file": "src/lib_tree_encoding/test/test_encoding.ml",
    "title": "test lib tree encoding: Encodings (Return)",
    "tags": [
      "alcotezt",
      "quick"
    ],
    "successful_runs": {
      "total_time": "148",
      "count": "1"
    }
  },
  {
    "file": "src/lib_store/unix/test/test_store.ml",
    "title": "tezos-store: store (block_of_identifier should fail to retrieve the checkpoint successor after the head)",
    "tags": [
      "alcotezt",
      "quick"
    ],
    "successful_runs": {
      "total_time": "38812",
      "count": "1"
    }
  },
  {
    "file": "src/lib_store/unix/test/test.ml",
    "title": "tezos-store: reconstruct (Reconstructing on a bootstrapped Full mode node with 101 blocks.)",
    "tags": [
      "alcotezt",
      "quick"
    ],
    "successful_runs": {
      "total_time": "1330143",
      "count": "1"
    }
  },
  {
    "file": "src/lib_store/unix/test/test.ml",
    "title": "tezos-store: history_mode_switch (switching from Rolling mode + 5 extra cycles to Rolling mode + 5 extra cycles with 72 blocks baked and cycle length 8)",
    "tags": [
      "alcotezt",
      "quick"
    ],
    "successful_runs": {
      "total_time": "1114136",
      "count": "1"
    }
  },
  {
    "file": "src/lib_store/unix/test/test.ml",
    "title": "tezos-store: history_mode_switch (switching from Archive mode to Archive mode with 72 blocks baked and cycle length 8)",
    "tags": [
      "alcotezt",
      "quick"
    ],
    "successful_runs": {
      "total_time": "1348082",
      "count": "1"
    }
  },
  {
    "file": "src/lib_stdlib/test-unix/test_circular_buffer.ml",
    "title": "tezos-stdlib: circular_buffer.constant-chunks.partial-write (bad-fit-underflow)",
    "tags": [
      "alcotezt",
      "quick"
    ],
    "successful_runs": {
      "total_time": "1384",
      "count": "1"
    }
  },
  {
    "file": "src/lib_stdlib/test/test_functionalArray.ml",
    "title": "stdlib: FunctionalArray (immutable_fallback)",
    "tags": [
      "alcotezt",
      "quick"
    ],
    "successful_runs": {
      "total_time": "283",
      "count": "1"
    }
  },
  {
    "file": "src/lib_shell/test/test_synchronisation_heuristic_fuzzy.ml",
    "title": "synchronisation heuristic fuzzy: synchronisation heuristic fuzzy (Shell.synchronisation_heuristic.equivalence-with-reference-implementation (threshold 4) (latency 100))",
    "tags": [
      "alcotezt",
      "slow"
    ],
    "successful_runs": {
      "total_time": "4533637",
      "count": "1"
    }
  },
  {
    "file": "src/lib_shell/test/test_synchronisation_heuristic.ml",
    "title": "tezos-shell: synchronisation heuristic sync (Threshold is one, update in the present)",
    "tags": [
      "alcotezt",
      "quick"
    ],
    "successful_runs": {
      "total_time": "12615",
      "count": "1"
    }
  },
  {
    "file": "src/lib_shell/test/test_shell_operation.ml",
    "title": "Shell_operation: Ddb leaks (handle_refused:64 calls)",
    "tags": [
      "alcotezt",
      "quick"
    ],
    "successful_runs": {
      "total_time": "696",
      "count": "1"
    }
  },
  {
    "file": "src/lib_shell/test/test_prevalidator_classification_operations.ml",
    "title": "Prevalidator: handle_operations ([handle_live_operations] path specification)",
    "tags": [
      "alcotezt",
      "slow"
    ],
    "successful_runs": {
      "total_time": "9928462",
      "count": "1"
    }
  },
  {
    "file": "src/lib_scoru_wasm/test/test_wasm_pvm.ml",
    "title": "test lib scoru wasm: WASM PVM (Test rebuild snapshotable state (2.0.0))",
    "tags": [
      "alcotezt",
      "quick"
    ],
    "successful_runs": {
      "total_time": "8126",
      "count": "1"
    }
  },
  {
    "file": "src/lib_scoru_wasm/test/test_output.ml",
    "title": "test lib scoru wasm: Output (Aux_write_output)",
    "tags": [
      "alcotezt",
      "quick"
    ],
    "successful_runs": {
      "total_time": "2182",
      "count": "1"
    }
  },
  {
    "file": "src/lib_scoru_wasm/test/test_hash_consistency.ml",
    "title": "test lib scoru wasm: Hash correspondence (Executions correspondence (ticks 30,000 to 35,000) (2.0.0-r1))",
    "tags": [
      "alcotezt",
      "quick"
    ],
    "successful_runs": {
      "total_time": "83864978",
      "count": "1"
    }
  },
  {
    "file": "src/lib_scoru_wasm/test/test_get_set.ml",
    "title": "test lib scoru wasm: Set/get (Set input (2.0.0))",
    "tags": [
      "alcotezt",
      "quick"
    ],
    "successful_runs": {
      "total_time": "602",
      "count": "1"
    }
  },
  {
    "file": "src/lib_scoru_wasm/test/test_durable_storage.ml",
    "title": "test lib scoru wasm: Durable storage (store_copy (2.0.0-r1))",
    "tags": [
      "alcotezt",
      "quick"
    ],
    "successful_runs": {
      "total_time": "1178",
      "count": "1"
    }
  },
  {
    "file": "src/lib_scoru_wasm/fast/test/test_fast.ml",
    "title": "test lib scoru-wasm-fast: Fast Execution (Computation kernel (2.0.0-r1))",
    "tags": [
      "alcotezt",
      "quick"
    ],
    "successful_runs": {
      "total_time": "613637",
      "count": "1"
    }
  },
  {
    "file": "src/lib_sapling/test/test_keys.ml",
    "title": "sapling: keys (zip32)",
    "tags": [
      "alcotezt",
      "quick"
    ],
    "successful_runs": {
      "total_time": "2186",
      "count": "1"
    }
  },
  {
    "file": "src/lib_rpc_http/test/test_rpc_http.ml",
    "title": "tezos-rpc-http: qcheck (put_policy preserves existing entries.)",
    "tags": [
      "alcotezt",
      "slow"
    ],
    "successful_runs": {
      "total_time": "74470",
      "count": "1"
    }
  },
  {
    "file": "src/lib_protocol_environment/test_shell_context/test_proxy_context.ml",
    "title": "tezos-shell-proxy-context: proxy_context (list)",
    "tags": [
      "alcotezt",
      "quick"
    ],
    "successful_runs": {
      "total_time": "411",
      "count": "1"
    }
  },
  {
    "file": "src/lib_polynomial/test/test_with_finite_field.ml",
    "title": "Polynomials with F379 and some random prime fields: Test lagrange interpolation, prime field order 960886889 (test random number of points)",
    "tags": [
      "alcotezt",
      "quick"
    ],
    "successful_runs": {
      "total_time": "231",
      "count": "1"
    }
  },
  {
    "file": "src/lib_polynomial/test/test_with_finite_field.ml",
    "title": "Polynomials with F379 and some random prime fields: Polynomial multiplication for prime field 153401719 (test properties nullifier 0 * P = P * 0 = 0)",
    "tags": [
      "alcotezt",
      "quick"
    ],
    "successful_runs": {
      "total_time": "212",
      "count": "1"
    }
  },
  {
    "file": "src/lib_polynomial/test/test_with_finite_field.ml",
    "title": "Polynomials with F379 and some random prime fields: Euclidian division for prime field 850868987 (test vectors for random divided by constant)",
    "tags": [
      "alcotezt",
      "quick"
    ],
    "successful_runs": {
      "total_time": "152",
      "count": "1"
    }
  },
  {
    "file": "src/lib_polynomial/test/test_with_finite_field.ml",
    "title": "Polynomials with F379 and some random prime fields: Tests on degrees, field order = 379 (degree of constants is one)",
    "tags": [
      "alcotezt",
      "quick"
    ],
    "successful_runs": {
      "total_time": "141",
      "count": "1"
    }
  },
  {
    "file": "src/lib_polynomial/test/test_with_finite_field.ml",
    "title": "Polynomials with F379 and some random prime fields: Test evaluation, field order = 379 (evaluation test vectors)",
    "tags": [
      "alcotezt",
      "quick"
    ],
    "successful_runs": {
      "total_time": "159",
      "count": "1"
    }
  },
  {
    "file": "src/lib_mockup/test/test_persistence.ml",
    "title": "tezos-mockup: persistence (Classify an empty directory)",
    "tags": [
      "alcotezt",
      "quick"
    ],
    "successful_runs": {
      "total_time": "530",
      "count": "1"
    }
  },
  {
    "file": "src/lib_mec/test/test_vesta_projective.ml",
    "title": "Vesta projective coordinates: equality (zero)",
    "tags": [
      "alcotezt",
      "quick"
    ],
    "successful_runs": {
      "total_time": "152",
      "count": "1"
    }
  },
  {
    "file": "src/lib_mec/test/test_vesta_jacobian.ml",
    "title": "Vesta jacobian coordinates: value generation (double_with_one)",
    "tags": [
      "alcotezt",
      "quick"
    ],
    "successful_runs": {
      "total_time": "156",
      "count": "1"
    }
  },
  {
    "file": "src/lib_mec/test/test_vesta_affine.ml",
    "title": "Vesta affine coordinates: value generation (negate_with_one)",
    "tags": [
      "alcotezt",
      "quick"
    ],
    "successful_runs": {
      "total_time": "128",
      "count": "1"
    }
  },
  {
    "file": "src/lib_mec/test/test_vesta_affine.ml",
    "title": "Vesta affine coordinates: Compressed representation (of_compressed_bytes_exn/opt do not accept uncompressed bytes representation)",
    "tags": [
      "alcotezt",
      "quick"
    ],
    "successful_runs": {
      "total_time": "26702",
      "count": "1"
    }
  },
  {
    "file": "src/lib_mec/test/test_tweedledum_projective.ml",
    "title": "Tweedledum projective coordinates: Group properties (opposite_of_scalar_is_opposite_of_ec)",
    "tags": [
      "alcotezt",
      "quick"
    ],
    "successful_runs": {
      "total_time": "1144581",
      "count": "1"
    }
  },
  {
    "file": "src/lib_mec/test/test_tweedledum_jacobian.ml",
    "title": "Tweedledum jacobian coordinates: Group properties (zero_scalar_nullifier_random)",
    "tags": [
      "alcotezt",
      "quick"
    ],
    "successful_runs": {
      "total_time": "59703",
      "count": "1"
    }
  },
  {
    "file": "src/lib_mec/test/test_tweedledum_affine.ml",
    "title": "Tweedledum affine coordinates: equality (zero)",
    "tags": [
      "alcotezt",
      "quick"
    ],
    "successful_runs": {
      "total_time": "11240",
      "count": "1"
    }
  },
  {
    "file": "src/lib_mec/test/test_tweedledee_projective.ml",
    "title": "Tweedledee projective coordinates: value generation (negate_with_zero)",
    "tags": [
      "alcotezt",
      "quick"
    ],
    "successful_runs": {
      "total_time": "180",
      "count": "1"
    }
  },
  {
    "file": "src/lib_mec/test/test_tweedledee_projective.ml",
    "title": "Tweedledee projective coordinates: Group properties (Generator is of prime order)",
    "tags": [
      "alcotezt",
      "quick"
    ],
    "successful_runs": {
      "total_time": "137",
      "count": "1"
    }
  },
  {
    "file": "src/lib_mec/test/test_tweedledee_jacobian.ml",
    "title": "Tweedledee jacobian coordinates: Group properties (check_bytes_one)",
    "tags": [
      "alcotezt",
      "quick"
    ],
    "successful_runs": {
      "total_time": "169",
      "count": "1"
    }
  },
  {
    "file": "src/lib_mec/test/test_tweedledee_affine.ml",
    "title": "Tweedledee affine coordinates: Group properties (check_bytes_random_sum)",
    "tags": [
      "alcotezt",
      "quick"
    ],
    "successful_runs": {
      "total_time": "96340",
      "count": "1"
    }
  },
  {
    "file": "src/lib_mec/test/test_secp256r1_projective.ml",
    "title": "secp256r1 projective coordinates: equality (random_same_objects)",
    "tags": [
      "alcotezt",
      "quick"
    ],
    "successful_runs": {
      "total_time": "7461",
      "count": "1"
    }
  },
  {
    "file": "src/lib_mec/test/test_secp256r1_jacobian.ml",
    "title": "secp256r1 jacobian coordinates: value generation (double generates a valid point)",
    "tags": [
      "alcotezt",
      "quick"
    ],
    "successful_runs": {
      "total_time": "9147",
      "count": "1"
    }
  },
  {
    "file": "src/lib_mec/test/test_secp256r1_affine.ml",
    "title": "secp256r1 affine coordinates: value generation (negate generates a valid point)",
    "tags": [
      "alcotezt",
      "quick"
    ],
    "successful_runs": {
      "total_time": "7397",
      "count": "1"
    }
  },
  {
    "file": "src/lib_mec/test/test_secp256k1_projective.ml",
    "title": "secp256k1 projective coordinates: value generation (of_bytes_exn and to_bytes are inverse functions)",
    "tags": [
      "alcotezt",
      "quick"
    ],
    "successful_runs": {
      "total_time": "8177",
      "count": "1"
    }
  },
  {
    "file": "src/lib_mec/test/test_secp256k1_projective.ml",
    "title": "secp256k1 projective coordinates: Group properties (additive_associativity_with_scalar)",
    "tags": [
      "alcotezt",
      "quick"
    ],
    "successful_runs": {
      "total_time": "1378654",
      "count": "1"
    }
  },
  {
    "file": "src/lib_mec/test/test_secp256k1_jacobian.ml",
    "title": "secp256k1 jacobian coordinates: Group properties (check_bytes_random_double)",
    "tags": [
      "alcotezt",
      "quick"
    ],
    "successful_runs": {
      "total_time": "22980",
      "count": "1"
    }
  },
  {
    "file": "src/lib_mec/test/test_secp256k1_affine.ml",
    "title": "secp256k1 affine coordinates: Group properties (double)",
    "tags": [
      "alcotezt",
      "quick"
    ],
    "successful_runs": {
      "total_time": "10679",
      "count": "1"
    }
  },
  {
    "file": "src/lib_mec/test/test_pallas_projective.ml",
    "title": "Pallas projective coordinates: value generation (double generates a valid point)",
    "tags": [
      "alcotezt",
      "quick"
    ],
    "successful_runs": {
      "total_time": "40138",
      "count": "1"
    }
  },
  {
    "file": "src/lib_mec/test/test_pallas_jacobian.ml",
    "title": "Pallas jacobian coordinates: value generation (negate generates a valid point)",
    "tags": [
      "alcotezt",
      "quick"
    ],
    "successful_runs": {
      "total_time": "29119",
      "count": "1"
    }
  },
  {
    "file": "src/lib_mec/test/test_pallas_affine.ml",
    "title": "Pallas affine coordinates: value generation (of_bytes_exn and to_bytes are inverse functions)",
    "tags": [
      "alcotezt",
      "quick"
    ],
    "successful_runs": {
      "total_time": "28918",
      "count": "1"
    }
  },
  {
    "file": "src/lib_mec/test/test_pallas_affine.ml",
    "title": "Pallas affine coordinates: Group properties (additive_associativity)",
    "tags": [
      "alcotezt",
      "quick"
    ],
    "successful_runs": {
      "total_time": "109566",
      "count": "1"
    }
  },
  {
    "file": "src/lib_mec/test/test_marvellous.ml",
    "title": "Marvellous permutation: Built on scalar field of BLS12-381 (Regression tests)",
    "tags": [
      "alcotezt",
      "quick"
    ],
    "successful_runs": {
      "total_time": "5324",
      "count": "1"
    }
  },
  {
    "file": "src/lib_mec/test/test_jubjub_weierstrass.ml",
    "title": "Jubjub - Weierstrass - Affine coordinates: value generation (double_with_one)",
    "tags": [
      "alcotezt",
      "quick"
    ],
    "successful_runs": {
      "total_time": "172",
      "count": "1"
    }
  },
  {
    "file": "src/lib_mec/test/test_jubjub_weierstrass.ml",
    "title": "Jubjub - Weierstrass - Affine coordinates: Compressed representation (Compressed representation of zero is the bs with zeroes)",
    "tags": [
      "alcotezt",
      "quick"
    ],
    "successful_runs": {
      "total_time": "193",
      "count": "1"
    }
  },
  {
    "file": "src/lib_mec/test/test_jubjub.ml",
    "title": "Jubjub: Group properties (zero is the identity)",
    "tags": [
      "alcotezt",
      "quick"
    ],
    "successful_runs": {
      "total_time": "66313",
      "count": "1"
    }
  },
  {
    "file": "src/lib_mec/test/test_iso_pallas_affine.ml",
    "title": "Iso Pallas affine form: Group properties (mul_by_order_of_base_field_equals_element)",
    "tags": [
      "alcotezt",
      "quick"
    ],
    "successful_runs": {
      "total_time": "1176249",
      "count": "1"
    }
  },
  {
    "file": "src/lib_mec/test/test_curve448.ml",
    "title": "Curve448: value generation (double_with_random)",
    "tags": [
      "alcotezt",
      "quick"
    ],
    "successful_runs": {
      "total_time": "28910",
      "count": "1"
    }
  },
  {
    "file": "src/lib_mec/test/test_curve25519_montgomery.ml",
    "title": "Curve25519: value generation (of_bytes_exn and to_bytes are inverse functions)",
    "tags": [
      "alcotezt",
      "quick"
    ],
    "successful_runs": {
      "total_time": "21045",
      "count": "1"
    }
  },
  {
    "file": "src/lib_mec/test/test_curve25519_montgomery.ml",
    "title": "Curve25519: Group properties (additive_associativity)",
    "tags": [
      "alcotezt",
      "quick"
    ],
    "successful_runs": {
      "total_time": "91195",
      "count": "1"
    }
  },
  {
    "file": "src/lib_mec/test/test_curve25519_affine_edwards.ml",
    "title": "Curve25519 edwards form and affine coordinates: Group properties (check_bytes_random_multiplication)",
    "tags": [
      "alcotezt",
      "quick"
    ],
    "successful_runs": {
      "total_time": "469110",
      "count": "1"
    }
  },
  {
    "file": "src/lib_mec/test/test_bn254_projective.ml",
    "title": "BN254 projective form: Group properties (zero_scalar_nullifier_zero)",
    "tags": [
      "alcotezt",
      "quick"
    ],
    "successful_runs": {
      "total_time": "184",
      "count": "1"
    }
  },
  {
    "file": "src/lib_mec/test/test_bn254_jacobian.ml",
    "title": "BN254 jacobian coordinates: value generation (addition generates a valid point)",
    "tags": [
      "alcotezt",
      "quick"
    ],
    "successful_runs": {
      "total_time": "33515",
      "count": "1"
    }
  },
  {
    "file": "src/lib_mec/test/test_bn254_affine.ml",
    "title": "BN254 affine form: value generation (double_with_random)",
    "tags": [
      "alcotezt",
      "quick"
    ],
    "successful_runs": {
      "total_time": "8092",
      "count": "1"
    }
  },
  {
    "file": "src/lib_mec/test/test_bn254_affine.ml",
    "title": "BN254 affine form: Compressed representation (Compressed version is half the size)",
    "tags": [
      "alcotezt",
      "quick"
    ],
    "successful_runs": {
      "total_time": "12789",
      "count": "1"
    }
  },
  {
    "file": "src/lib_mec/test/test_bls12_381_projective.ml",
    "title": "BLS12-381 G1 projective form: Group properties (check_bytes_random)",
    "tags": [
      "alcotezt",
      "quick"
    ],
    "successful_runs": {
      "total_time": "517395",
      "count": "1"
    }
  },
  {
    "file": "src/lib_mec/test/test_bls12_381_affine.ml",
    "title": "BLS12-381 G1 affine form: Group properties (check_bytes_zero)",
    "tags": [
      "alcotezt",
      "quick"
    ],
    "successful_runs": {
      "total_time": "300",
      "count": "1"
    }
  },
  {
    "file": "src/lib_mec/test/test_bandersnatch_affine_weierstrass.ml",
    "title": "Bandersnatch Weierstrass form, affine coordinates: Group properties (zero_scalar_nullifier_random)",
    "tags": [
      "alcotezt",
      "quick"
    ],
    "successful_runs": {
      "total_time": "32578",
      "count": "1"
    }
  },
  {
    "file": "src/lib_mec/test/test_bandersnatch_affine_montgomery.ml",
    "title": "Bandersnatch Montgomery form and affine coordinates: value generation (double_with_zero)",
    "tags": [
      "alcotezt",
      "quick"
    ],
    "successful_runs": {
      "total_time": "293",
      "count": "1"
    }
  },
  {
    "file": "src/lib_mec/test/test_bandersnatch_affine_edwards.ml",
    "title": "Bandersnatch Edwards form, affine coordinates: value generation (negate_with_zero)",
    "tags": [
      "alcotezt",
      "quick"
    ],
    "successful_runs": {
      "total_time": "191",
      "count": "1"
    }
  },
  {
    "file": "src/lib_mec/test/test_bandersnatch_affine_edwards.ml",
    "title": "Bandersnatch Edwards form, affine coordinates: Group properties (additive_associativity_with_scalar)",
    "tags": [
      "alcotezt",
      "quick"
    ],
    "successful_runs": {
      "total_time": "1821264",
      "count": "1"
    }
  },
  {
    "file": "src/lib_mec/test/test_babyjubjub_reduced.ml",
    "title": "BabyJubjub reduced twisted edwards form: Group properties (opposite_of_zero_is_zero)",
    "tags": [
      "alcotezt",
      "quick"
    ],
    "successful_runs": {
      "total_time": "299",
      "count": "1"
    }
  },
  {
    "file": "src/lib_mec/test/test_babyjubjub.ml",
    "title": "BabyJubjub: Group properties (multiplication_properties_on_base_field_element)",
    "tags": [
      "alcotezt",
      "quick"
    ],
    "successful_runs": {
      "total_time": "3131185",
      "count": "1"
    }
  },
  {
    "file": "src/lib_lwt_result_stdlib/test/test_list_basic_lwt.ml",
    "title": "list-basic-lwt: init (init_es)",
    "tags": [
      "alcotezt",
      "quick"
    ],
    "successful_runs": {
      "total_time": "180",
      "count": "1"
    }
  },
  {
    "file": "src/lib_lwt_result_stdlib/test/test_fuzzing_list_against_stdlib.ml",
    "title": "FuzzRef: List (List.remove_assoc)",
    "tags": [
      "alcotezt",
      "slow"
    ],
    "successful_runs": {
      "total_time": "295661",
      "count": "1"
    }
  },
  {
    "file": "src/lib_crypto/test/test_run.ml",
    "title": "tezos-crypto: signature (test_of_bytes_without_validation)",
    "tags": [
      "alcotezt",
      "quick"
    ],
    "successful_runs": {
      "total_time": "1446",
      "count": "1"
    }
  },
  {
    "file": "src/lib_crypto/test/test_run.ml",
    "title": "tezos-crypto: crypto_box (Neuterize Secret roundtrip)",
    "tags": [
      "alcotezt",
      "quick"
    ],
    "successful_runs": {
      "total_time": "201",
      "count": "1"
    }
  },
  {
    "file": "src/lib_context/test/test_context.ml",
    "title": "tezos-context: context (memory:fold_keys_undefined)",
    "tags": [
      "alcotezt",
      "quick"
    ],
    "successful_runs": {
      "total_time": "3113",
      "count": "1"
    }
  },
  {
    "file": "src/lib_clic/test/test_clic.ml",
    "title": "Tezos_clic: dispatch (advanced)",
    "tags": [
      "alcotezt",
      "quick"
    ],
    "successful_runs": {
      "total_time": "697",
      "count": "1"
    }
  },
  {
    "file": "src/lib_bls12_381_polynomial/test/test_main.ml",
    "title": "PlonK: Domains (build_domain_power_of_two)",
    "tags": [
      "alcotezt",
      "quick"
    ],
    "successful_runs": {
      "total_time": "5257",
      "count": "1"
    }
  },
  {
    "file": "src/lib_bls12_381_polynomial/test/test_main.ml",
    "title": "PlonK: Polynomial_c (division_x_z)",
    "tags": [
      "alcotezt",
      "quick"
    ],
    "successful_runs": {
      "total_time": "295258",
      "count": "1"
    }
  },
  {
    "file": "src/lib_bls12_381_polynomial/test/test_main.ml",
    "title": "PlonK: Srs (pippenger)",
    "tags": [
      "alcotezt",
      "quick"
    ],
    "successful_runs": {
      "total_time": "1163",
      "count": "1"
    }
  },
  {
    "file": "src/lib_benchmark/test/test_sparse_vec.ml",
    "title": "tezos-benchmark: sparse_vec (eval1)",
    "tags": [
      "alcotezt",
      "quick"
    ],
    "successful_runs": {
      "total_time": "174",
      "count": "1"
    }
  },
  {
    "file": "src/lib_base/test/test_sized.ml",
    "title": "Sized: SizedSet (union)",
    "tags": [
      "alcotezt",
      "slow"
    ],
    "successful_runs": {
      "total_time": "874",
      "count": "1"
    }
  },
  {
    "file": "src/lib_base/test/test_bounded.ml",
    "title": "Bounded: Int32 (Uint16.tight bounds)",
    "tags": [
      "alcotezt",
      "quick"
    ],
    "successful_runs": {
      "total_time": "180",
      "count": "1"
    }
  },
  {
    "file": "tezt/tests/bootstrap.ml",
    "title": "RPC force bootstrapped",
    "tags": [
      "rpc",
      "bootstrapped"
    ],
    "successful_runs": {
      "total_time": "5438879",
      "count": "1"
    }
  },
  {
    "file": "tezt/tests/sc_rollup.ml",
    "title": "Nairobi->Alpha: arith - Test to cement a commitment made pre migration then publish a new commitment.",
    "tags": [
      "nairobi",
      "alpha",
      "arith",
      "migration",
      "commitment",
      "cement"
    ],
    "successful_runs": {
      "total_time": "50467489",
      "count": "1"
    }
  },
  {
    "file": "tezt/tests/baker_test.ml",
    "title": "Alpha: No BLS baker test",
    "tags": [
      "alpha",
      "node",
      "baker",
      "bls"
    ],
    "successful_runs": {
      "total_time": "15448098",
      "count": "1"
    }
  },
  {
    "file": "tezt/tests/baking.ml",
    "title": "Alpha: ensure we can still bake with a faulty operation",
    "tags": [
      "alpha",
      "baking",
      "exception"
    ],
    "successful_runs": {
      "total_time": "17261482",
      "count": "1"
    }
  },
  {
    "file": "tezt/tests/baking.ml",
    "title": "Alpha: External operations are ordered (5 transfers, max 3 operations)",
    "tags": [
      "alpha",
      "operations_pool",
      "baking"
    ],
    "successful_runs": {
      "total_time": "22783804",
      "count": "1"
    }
  },
  {
    "file": "tezt/tests/basic.ml",
    "title": "Mumbai: node initialization (rolling mode)",
    "tags": [
      "mumbai",
      "basic",
      "node",
      "rolling"
    ],
    "successful_runs": {
      "total_time": "16098351",
      "count": "1"
    }
  },
  {
    "file": "tezt/tests/client_fa12.ml",
    "title": "Alpha: test fa1.2, get balance offchain [mini_scenarios/lqt_fa12.mligo]",
    "tags": [
      "alpha",
      "client",
      "fa12",
      "lqt_fa12_mligo"
    ],
    "successful_runs": {
      "total_time": "5409878",
      "count": "1"
    }
  },
  {
    "file": "tezt/tests/client_fa12.ml",
    "title": "Nairobi: test fa1.2, get allowance offchain [mini_scenarios/fa12_reference]",
    "tags": [
      "nairobi",
      "client",
      "fa12",
      "fa12_reference"
    ],
    "successful_runs": {
      "total_time": "5701556",
      "count": "1"
    }
  },
  {
    "file": "tezt/tests/client_run_view.ml",
    "title": "Alpha: Run view `value` without input",
    "tags": [
      "alpha",
      "client",
      "michelson",
      "view"
    ],
    "successful_runs": {
      "total_time": "2721937",
      "count": "1"
    }
  },
  {
    "file": "tezt/tests/consensus_key.ml",
    "title": "Nairobi: update consensus key",
    "tags": [
      "nairobi",
      "consensus_key"
    ],
    "successful_runs": {
      "total_time": "85373059",
      "count": "1"
    }
  },
  {
    "file": "tezt/tests/contract_big_map_to_self.ml",
    "title": "Alpha: Test sending big_map to self",
    "tags": [
      "alpha",
      "client",
      "michelson"
    ],
    "successful_runs": {
      "total_time": "3231866",
      "count": "1"
    }
  },
  {
    "file": "tezt/tests/contract_hash_fun.ml",
    "title": "Nairobi: Test contract hash function: sha3",
    "tags": [
      "nairobi",
      "michelson",
      "crypto",
      "contract",
      "hash",
      "sha3"
    ],
    "successful_runs": {
      "total_time": "34487179",
      "count": "1"
    }
  },
  {
    "file": "tezt/tests/contract_onchain_opcodes.ml",
    "title": "Alpha: Contract onchain opcodes: test_store_input",
    "tags": [
      "regression",
      "alpha",
      "contract",
      "onchain",
      "opcodes"
    ],
    "successful_runs": {
      "total_time": "6102353",
      "count": "1"
    }
  },
  {
    "file": "tezt/tests/contract_onchain_opcodes.ml",
    "title": "Nairobi: Contract onchain opcodes: ticket_non_fungible",
    "tags": [
      "nairobi",
      "contract",
      "onchain",
      "opcodes"
    ],
    "successful_runs": {
      "total_time": "24254063",
      "count": "1"
    }
  },
  {
    "file": "tezt/tests/contract_opcodes.ml",
    "title": "Alpha: opcodes [reverse--storage528921618--input851203613]",
    "tags": [
      "regression",
      "alpha",
      "michelson"
    ],
    "successful_runs": {
      "total_time": "905702",
      "count": "1"
    }
  },
  {
    "file": "tezt/tests/contract_opcodes.ml",
    "title": "Mumbai: opcodes [loop_left--storage528921618--input851203613]",
    "tags": [
      "regression",
      "mumbai",
      "michelson"
    ],
    "successful_runs": {
      "total_time": "1187103",
      "count": "1"
    }
  },
  {
    "file": "tezt/tests/contract_opcodes.ml",
    "title": "Alpha: opcodes [slice--storage364922380--input551316239]",
    "tags": [
      "regression",
      "alpha",
      "michelson"
    ],
    "successful_runs": {
      "total_time": "1272371",
      "count": "1"
    }
  },
  {
    "file": "tezt/tests/contract_opcodes.ml",
    "title": "Mumbai: opcodes [slice_bytes--storage229749865--input743596105]",
    "tags": [
      "regression",
      "mumbai",
      "michelson"
    ],
    "successful_runs": {
      "total_time": "1060546",
      "count": "1"
    }
  },
  {
    "file": "tezt/tests/contract_opcodes.ml",
    "title": "Nairobi: opcodes [pair_id--storage921624073--input181204719]",
    "tags": [
      "regression",
      "nairobi",
      "michelson"
    ],
    "successful_runs": {
      "total_time": "897979",
      "count": "1"
    }
  },
  {
    "file": "tezt/tests/contract_opcodes.ml",
    "title": "Mumbai: opcodes [not_binary--storage921624073--input24243730]",
    "tags": [
      "regression",
      "mumbai",
      "michelson"
    ],
    "successful_runs": {
      "total_time": "951395",
      "count": "1"
    }
  },
  {
    "file": "tezt/tests/contract_opcodes.ml",
    "title": "Nairobi: opcodes [xor--storage921624073--input967929605]",
    "tags": [
      "regression",
      "nairobi",
      "michelson"
    ],
    "successful_runs": {
      "total_time": "720307",
      "count": "1"
    }
  },
  {
    "file": "tezt/tests/contract_opcodes.ml",
    "title": "Nairobi: opcodes [shifts--storage921624073--input485030042]",
    "tags": [
      "regression",
      "nairobi",
      "michelson"
    ],
    "successful_runs": {
      "total_time": "875586",
      "count": "1"
    }
  },
  {
    "file": "tezt/tests/contract_opcodes.ml",
    "title": "Alpha: opcodes [concat_list--storage79230375--input264787654]",
    "tags": [
      "regression",
      "alpha",
      "michelson"
    ],
    "successful_runs": {
      "total_time": "1101207",
      "count": "1"
    }
  },
  {
    "file": "tezt/tests/contract_opcodes.ml",
    "title": "Mumbai: opcodes [big_map_mem_nat--storage690637660--input453441034]",
    "tags": [
      "regression",
      "mumbai",
      "michelson"
    ],
    "successful_runs": {
      "total_time": "1188462",
      "count": "1"
    }
  },
  {
    "file": "tezt/tests/contract_opcodes.ml",
    "title": "Nairobi: opcodes [list_concat_bytes--storage726220441--input972761363]",
    "tags": [
      "regression",
      "nairobi",
      "michelson"
    ],
    "successful_runs": {
      "total_time": "1062865",
      "count": "1"
    }
  },
  {
    "file": "tezt/tests/contract_opcodes.ml",
    "title": "Alpha: opcodes [list_iter--storage680650890--input568817463]",
    "tags": [
      "regression",
      "alpha",
      "michelson"
    ],
    "successful_runs": {
      "total_time": "896447",
      "count": "1"
    }
  },
  {
    "file": "tezt/tests/contract_opcodes.ml",
    "title": "Nairobi: opcodes [map_size--storage492856247--input15265129]",
    "tags": [
      "regression",
      "nairobi",
      "michelson"
    ],
    "successful_runs": {
      "total_time": "581964",
      "count": "1"
    }
  },
  {
    "file": "tezt/tests/contract_opcodes.ml",
    "title": "Mumbai: opcodes [contains_all--storage921624073--input917967660]",
    "tags": [
      "regression",
      "mumbai",
      "michelson"
    ],
    "successful_runs": {
      "total_time": "882905",
      "count": "1"
    }
  },
  {
    "file": "tezt/tests/contract_opcodes.ml",
    "title": "Mumbai: opcodes [get_map_value--storage139236239--input329240220]",
    "tags": [
      "regression",
      "mumbai",
      "michelson"
    ],
    "successful_runs": {
      "total_time": "1118668",
      "count": "1"
    }
  },
  {
    "file": "tezt/tests/contract_opcodes.ml",
    "title": "Alpha: opcodes [exec_concat--storage398998998--input79230375]",
    "tags": [
      "regression",
      "alpha",
      "michelson"
    ],
    "successful_runs": {
      "total_time": "1009390",
      "count": "1"
    }
  },
  {
    "file": "tezt/tests/contract_opcodes.ml",
    "title": "Mumbai: opcodes [set_cdr--storage205576101--input654274102]",
    "tags": [
      "regression",
      "mumbai",
      "michelson"
    ],
    "successful_runs": {
      "total_time": "1198724",
      "count": "1"
    }
  },
  {
    "file": "tezt/tests/contract_opcodes.ml",
    "title": "Nairobi: opcodes [add_timestamp_delta--storage921624073--input373737581]",
    "tags": [
      "regression",
      "nairobi",
      "michelson"
    ],
    "successful_runs": {
      "total_time": "1111184",
      "count": "1"
    }
  },
  {
    "file": "tezt/tests/contract_opcodes.ml",
    "title": "Nairobi: opcodes [ediv_mutez--storage977883604--input44513000]",
    "tags": [
      "regression",
      "nairobi",
      "michelson"
    ],
    "successful_runs": {
      "total_time": "1076853",
      "count": "1"
    }
  },
  {
    "file": "tezt/tests/contract_opcodes.ml",
    "title": "Nairobi: opcodes [comparisons--storage457300675--input281780712]",
    "tags": [
      "regression",
      "nairobi",
      "michelson"
    ],
    "successful_runs": {
      "total_time": "1070492",
      "count": "1"
    }
  },
  {
    "file": "tezt/tests/contract_opcodes.ml",
    "title": "Alpha: opcodes [neg--storage680650890--input1067298059]",
    "tags": [
      "regression",
      "alpha",
      "michelson"
    ],
    "successful_runs": {
      "total_time": "1123508",
      "count": "1"
    }
  },
  {
    "file": "tezt/tests/contract_opcodes.ml",
    "title": "Alpha: opcodes [bls12_381_fr_z_nat--storage994282947--input453441034]",
    "tags": [
      "regression",
      "alpha",
      "michelson"
    ],
    "successful_runs": {
      "total_time": "963353",
      "count": "1"
    }
  },
  {
    "file": "tezt/tests/contract_opcodes.ml",
    "title": "Nairobi: opcodes [bls12_381_fr_z_int--storage994282947--input680650890]",
    "tags": [
      "regression",
      "nairobi",
      "michelson"
    ],
    "successful_runs": {
      "total_time": "705310",
      "count": "1"
    }
  },
  {
    "file": "tezt/tests/contract_opcodes.ml",
    "title": "Mumbai: opcodes [bls12_381_z_fr_int--storage994282947--input585234482]",
    "tags": [
      "regression",
      "mumbai",
      "michelson"
    ],
    "successful_runs": {
      "total_time": "750967",
      "count": "1"
    }
  },
  {
    "file": "tezt/tests/contract_opcodes.ml",
    "title": "Alpha: opcodes [and_bytes--storage125992234--input125992234]",
    "tags": [
      "regression",
      "alpha",
      "michelson"
    ],
    "successful_runs": {
      "total_time": "514088",
      "count": "1"
    }
  },
  {
    "file": "tezt/tests/contract_opcodes.ml",
    "title": "Mumbai: test Michelson opcodes: LEVEL",
    "tags": [
      "regression",
      "mumbai",
      "michelson"
    ],
    "successful_runs": {
      "total_time": "1510574",
      "count": "1"
    }
  },
  {
    "file": "tezt/tests/contract_macros.ml",
    "title": "Alpha: macros [max_in_list--storage921624073--input802622031]",
    "tags": [
      "alpha",
      "michelson",
      "macros"
    ],
    "successful_runs": {
      "total_time": "754172",
      "count": "1"
    }
  },
  {
    "file": "tezt/tests/contract_macros.ml",
    "title": "Mumbai: macros [assert_cmpge--storage125992234--input1011138251]",
    "tags": [
      "mumbai",
      "michelson",
      "macros"
    ],
    "successful_runs": {
      "total_time": "486748",
      "count": "1"
    }
  },
  {
    "file": "tezt/tests/contract_macros.ml",
    "title": "Nairobi: macros [compare_bytes--storage457300675--input718599173]",
    "tags": [
      "nairobi",
      "michelson",
      "macros"
    ],
    "successful_runs": {
      "total_time": "486246",
      "count": "1"
    }
  },
  {
    "file": "tezt/tests/contract_macros.ml",
    "title": "Alpha: macro failure [assert_eq--storage125992234--input694127922]",
    "tags": [
      "alpha",
      "michelson",
      "macros"
    ],
    "successful_runs": {
      "total_time": "600707",
      "count": "1"
    }
  },
  {
    "file": "tezt/tests/contract_macros.ml",
    "title": "Nairobi: macro failure [assert_cmpge--storage125992234--input280547028]",
    "tags": [
      "nairobi",
      "michelson",
      "macros"
    ],
    "successful_runs": {
      "total_time": "724394",
      "count": "1"
    }
  },
  {
    "file": "tezt/tests/contract_macros.ml",
    "title": "Alpha: Macro expansion: macros/build_list",
    "tags": [
      "regression",
      "alpha",
      "michelson",
      "macros"
    ],
    "successful_runs": {
      "total_time": "710191",
      "count": "1"
    }
  },
  {
    "file": "tezt/tests/contract_macros.ml",
    "title": "Mumbai: Macro expansion: macros/assert_cmpeq",
    "tags": [
      "regression",
      "mumbai",
      "michelson",
      "macros"
    ],
    "successful_runs": {
      "total_time": "555795",
      "count": "1"
    }
  },
  {
    "file": "tezt/tests/contract_macros.ml",
    "title": "Nairobi: Macro expansion: macros/take_my_money",
    "tags": [
      "regression",
      "nairobi",
      "michelson",
      "macros"
    ],
    "successful_runs": {
      "total_time": "551980",
      "count": "1"
    }
  },
  {
    "file": "tezt/tests/encoding.ml",
    "title": "Alpha: protocol encoding regression test: block_header",
    "tags": [
      "regression",
      "alpha",
      "encoding",
      "protocol",
      "block_header"
    ],
    "successful_runs": {
      "total_time": "1211660",
      "count": "1"
    }
  },
  {
    "file": "tezt/tests/encoding.ml",
    "title": "Mumbai: protocol encoding regression test: operation.raw",
    "tags": [
      "regression",
      "mumbai",
      "encoding",
      "protocol",
      "operation",
      "raw"
    ],
    "successful_runs": {
      "total_time": "979742",
      "count": "1"
    }
  },
  {
    "file": "tezt/tests/global_constants.ml",
    "title": "Nairobi: Global constants are expanded on entrypoints RPC",
    "tags": [
      "nairobi",
      "global_constant",
      "rpc"
    ],
    "successful_runs": {
      "total_time": "7954938",
      "count": "1"
    }
  },
  {
    "file": "tezt/tests/light.ml",
    "title": "Mumbai: (Light) Wrong proto",
    "tags": [
      "mumbai",
      "light",
      "proto"
    ],
    "successful_runs": {
      "total_time": "7843690",
      "count": "1"
    }
  },
  {
    "file": "tezt/tests/manager_operations.ml",
    "title": "Mumbai: Simple transfer applied",
    "tags": [
      "mumbai",
      "transaction",
      "transfer"
    ],
    "successful_runs": {
      "total_time": "10729477",
      "count": "1"
    }
  },
  {
    "file": "tezt/tests/manager_operations.ml",
    "title": "Alpha: Simple transfer with wrong signature",
    "tags": [
      "alpha",
      "transaction",
      "transfer"
    ],
    "successful_runs": {
      "total_time": "10841127",
      "count": "1"
    }
  },
  {
    "file": "tezt/tests/mockup.ml",
    "title": "Mumbai: (Mockup) Transfer",
    "tags": [
      "mumbai",
      "mockup",
      "client",
      "transfer"
    ],
    "successful_runs": {
      "total_time": "4341861",
      "count": "1"
    }
  },
  {
    "file": "tezt/tests/mockup.ml",
    "title": "Alpha: (Mockup) Mockup config initialization failure.",
    "tags": [
      "alpha",
      "mockup",
      "client",
      "config",
      "initialization"
    ],
    "successful_runs": {
      "total_time": "1152602",
      "count": "1"
    }
  },
  {
    "file": "tezt/tests/mockup.ml",
    "title": "Nairobi: (Mockup) Mockup config initialization failure.",
    "tags": [
      "nairobi",
      "mockup",
      "client",
      "config",
      "initialization"
    ],
    "successful_runs": {
      "total_time": "1291435",
      "count": "1"
    }
  },
  {
    "file": "tezt/tests/prevalidator.ml",
    "title": "Mumbai: Test private/injection/operations RPC",
    "tags": [
      "mumbai",
      "mempool",
      "injection",
      "operations",
      "rpc"
    ],
    "successful_runs": {
      "total_time": "19569342",
      "count": "1"
    }
  },
  {
    "file": "tezt/tests/proxy.ml",
    "title": "Alpha: (Proxy) (/chains/main/blocks/head/votes/ballots) No useless RPC call",
    "tags": [
      "alpha",
      "proxy",
      "rpc",
      "get"
    ],
    "successful_runs": {
      "total_time": "5237017",
      "count": "1"
    }
  },
  {
    "file": "tezt/tests/proxy.ml",
    "title": "Mumbai: (Proxy) (/chains/main/blocks/head/votes/total_voting_power) No useless RPC call",
    "tags": [
      "mumbai",
      "proxy",
      "rpc",
      "get"
    ],
    "successful_runs": {
      "total_time": "4839237",
      "count": "1"
    }
  },
  {
    "file": "tezt/tests/proxy.ml",
    "title": "Nairobi: (Proxy) (/chains/main/blocks/head/votes/ballots) No useless RPC call",
    "tags": [
      "nairobi",
      "proxy",
      "rpc",
      "get"
    ],
    "successful_runs": {
      "total_time": "5312206",
      "count": "1"
    }
  },
  {
    "file": "tezt/tests/RPC_test.ml",
    "title": "Alpha: (mode light) RPC tests: workers",
    "tags": [
      "alpha",
      "rpc",
      "light",
      "workers"
    ],
    "successful_runs": {
      "total_time": "10131599",
      "count": "1"
    }
  },
  {
    "file": "tezt/tests/RPC_test.ml",
    "title": "Nairobi: (mode light) RPC tests: workers",
    "tags": [
      "nairobi",
      "rpc",
      "light",
      "workers"
    ],
    "successful_runs": {
      "total_time": "9599768",
      "count": "1"
    }
  },
  {
    "file": "tezt/tests/RPC_test.ml",
    "title": "Mumbai: (mode proxy_server_data_dir) RPC regression tests: votes",
    "tags": [
      "regression",
      "mumbai",
      "rpc",
      "proxy_server_data_dir",
      "votes"
    ],
    "successful_runs": {
      "total_time": "22746381",
      "count": "1"
    }
  },
  {
    "file": "tezt/tests/replace_by_fees.ml",
    "title": "Nairobi: Replacing a batched op is possible if enough fees are provided",
    "tags": [
      "nairobi",
      "replace",
      "fee",
      "manager"
    ],
    "successful_runs": {
      "total_time": "13819057",
      "count": "1"
    }
  },
  {
    "file": "tezt/tests/sapling.ml",
    "title": "Mumbai: test sapling memo size",
    "tags": [
      "mumbai",
      "sapling",
      "shield",
      "memo_size"
    ],
    "successful_runs": {
      "total_time": "11145883",
      "count": "1"
    }
  },
  {
    "file": "tezt/tests/script_chain_id.ml",
    "title": "Mumbai: Chain ID Authentication",
    "tags": [
      "mumbai",
      "client",
      "contract"
    ],
    "successful_runs": {
      "total_time": "3589108",
      "count": "1"
    }
  },
  {
    "file": "tezt/tests/script_conversion.ml",
    "title": "Nairobi: convert script",
    "tags": [
      "nairobi",
      "michelson",
      "conversion"
    ],
    "successful_runs": {
      "total_time": "8360563",
      "count": "1"
    }
  },
  {
    "file": "tezt/tests/script_illtyped.ml",
    "title": "Mumbai: Test Deprecated Typecheck in Legacy - legacy/steps_to_quota",
    "tags": [
      "mumbai",
      "client",
      "script",
      "michelson",
      "typechecking"
    ],
    "successful_runs": {
      "total_time": "1189440",
      "count": "1"
    }
  },
  {
    "file": "tezt/tests/script_illtyped.ml",
    "title": "Mumbai: Test Ill Typecheck - stack_bottom_unpopable",
    "tags": [
      "mumbai",
      "client",
      "script",
      "michelson",
      "typechecking"
    ],
    "successful_runs": {
      "total_time": "1149679",
      "count": "1"
    }
  },
  {
    "file": "tezt/tests/script_illtyped.ml",
    "title": "Alpha: Test Ill Typecheck - contract_annotation_default",
    "tags": [
      "alpha",
      "client",
      "script",
      "michelson",
      "typechecking"
    ],
    "successful_runs": {
      "total_time": "1328676",
      "count": "1"
    }
  },
  {
    "file": "tezt/tests/script_illtyped.ml",
    "title": "Alpha: Test Ill Typecheck - uncomb1",
    "tags": [
      "alpha",
      "client",
      "script",
      "michelson",
      "typechecking"
    ],
    "successful_runs": {
      "total_time": "1346856",
      "count": "1"
    }
  },
  {
    "file": "tezt/tests/script_illtyped.ml",
    "title": "Nairobi: Test Ill Typecheck - push_big_map_with_id_without_parens",
    "tags": [
      "nairobi",
      "client",
      "script",
      "michelson",
      "typechecking"
    ],
    "successful_runs": {
      "total_time": "1123126",
      "count": "1"
    }
  },
  {
    "file": "tezt/tests/sc_rollup.ml",
    "title": "Nairobi: wasm_2_0_0 - refutation games winning strategies (pvm_proof_1)",
    "tags": [
      "regression",
      "nairobi",
      "sc_rollup",
      "wasm_2_0_0",
      "rollup_node",
      "refutation"
    ],
    "successful_runs": {
      "total_time": "126297391",
      "count": "1"
    }
  },
  {
    "file": "tezt/tests/sc_rollup.ml",
    "title": "Alpha: wasm_2_0_0 - refutation games winning strategies (pvm_proof_3)",
    "tags": [
      "regression",
      "alpha",
      "sc_rollup",
      "wasm_2_0_0",
      "rollup_node",
      "refutation"
    ],
    "successful_runs": {
      "total_time": "124081983",
      "count": "1"
    }
  },
  {
    "file": "tezt/tests/sc_rollup.ml",
    "title": "Nairobi: arith - reveal data fails with wrong hash",
    "tags": [
      "nairobi",
      "sc_rollup",
      "arith",
      "rollup_node",
      "reveals",
      "wrong"
    ],
    "successful_runs": {
      "total_time": "6417265",
      "count": "1"
    }
  },
  {
    "file": "tezt/tests/sc_rollup.ml",
    "title": "Alpha: wasm_2_0_0 - a late rollup should catch up",
    "tags": [
      "alpha",
      "sc_rollup",
      "wasm_2_0_0",
      "rollup_node",
      "late"
    ],
    "successful_runs": {
      "total_time": "74131844",
      "count": "1"
    }
  },
  {
    "file": "tezt/tests/sc_rollup.ml",
    "title": "Mumbai: wasm_2_0_0 - output exec (0, entrypoint: %aux, eager: 5, extern, no_parameters_ty)",
    "tags": [
      "mumbai",
      "sc_rollup",
      "wasm_2_0_0",
      "rollup_node",
      "outbox",
      "extern",
      "aux",
      "no_parameters_ty"
    ],
    "successful_runs": {
      "total_time": "15558543",
      "count": "1"
    }
  },
  {
    "file": "tezt/tests/sc_rollup.ml",
    "title": "Mumbai: arith - rollup node - correct handling of commitments (operator_publishes)",
    "tags": [
      "mumbai",
      "sc_rollup",
      "arith",
      "rollup_node",
      "commitment",
      "modes",
      "operator"
    ],
    "successful_runs": {
      "total_time": "177838577",
      "count": "1"
    }
  },
  {
    "file": "tezt/tests/sc_rollup.ml",
    "title": "Alpha: arith - rollup node - correct handling of commitments (non_final_level)",
    "tags": [
      "alpha",
      "sc_rollup",
      "arith",
      "rollup_node",
      "commitment"
    ],
    "successful_runs": {
      "total_time": "91529514",
      "count": "1"
    }
  },
  {
    "file": "tezt/tests/sc_rollup.ml",
    "title": "Nairobi: arith - a rollup should recover on interruption before first inbox",
    "tags": [
      "nairobi",
      "sc_rollup",
      "arith",
      "rollup_node",
      "interrupt"
    ],
    "successful_runs": {
      "total_time": "15911691",
      "count": "1"
    }
  },
  {
    "file": "tezt/tests/sc_rollup.ml",
    "title": "Mumbai: arith - output exec (0, entrypoint: %aux, eager: 0, intern, no_parameters_ty)",
    "tags": [
      "mumbai",
      "sc_rollup",
      "arith",
      "rollup_node",
      "outbox",
      "intern",
      "aux",
      "no_parameters_ty"
    ],
    "successful_runs": {
      "total_time": "19894002",
      "count": "1"
    }
  },
  {
    "file": "tezt/tests/sc_rollup.ml",
    "title": "Alpha: arith - output exec (0, entrypoint: %aux, eager: 0, extern, no_parameters_ty)",
    "tags": [
      "alpha",
      "sc_rollup",
      "arith",
      "rollup_node",
      "outbox",
      "extern",
      "aux",
      "no_parameters_ty"
    ],
    "successful_runs": {
      "total_time": "20900583",
      "count": "1"
    }
  },
  {
    "file": "tezt/tests/self_address_transfer.ml",
    "title": "Nairobi: Self address transfer",
    "tags": [
      "regression",
      "nairobi",
      "client",
      "michelson"
    ],
    "successful_runs": {
      "total_time": "2493017",
      "count": "1"
    }
  },
  {
    "file": "tezt/tests/tenderbake.ml",
    "title": "Nairobi: Tenderbake manual bake",
    "tags": [
      "nairobi",
      "propose",
      "endorse",
      "preendorse",
      "tenderbake",
      "low_level",
      "manual"
    ],
    "successful_runs": {
      "total_time": "14350778",
      "count": "1"
    }
  },
  {
    "file": "tezt/tests/test_contract_bls12_381.ml",
    "title": "Alpha: Bls12_381 contract primitives, g1: mul",
    "tags": [
      "regression",
      "alpha",
      "michelson",
      "crypto",
      "contract",
      "bls12_381",
      "g1",
      "mul"
    ],
    "successful_runs": {
      "total_time": "88639860",
      "count": "1"
    }
  },
  {
    "file": "tezt/tests/test_contract_bls12_381.ml",
    "title": "Nairobi: Bls12_381 contract primitives, g1: negate",
    "tags": [
      "regression",
      "nairobi",
      "michelson",
      "crypto",
      "contract",
      "bls12_381",
      "g1",
      "negate"
    ],
    "successful_runs": {
      "total_time": "8026296",
      "count": "1"
    }
  },
  {
    "file": "tezt/tests/tickets.ml",
    "title": "Mumbai: Minting then sending tickets to smart-contract rollup should succeed with appropriate ticket updates field in receipt.",
    "tags": [
      "regression",
      "mumbai",
      "client",
      "michelson"
    ],
    "successful_runs": {
      "total_time": "7898592",
      "count": "1"
    }
  },
  {
    "file": "tezt/tests/tzip4_view.ml",
    "title": "Mumbai: Run tzip4_view `tzip4_view_add`",
    "tags": [
      "mumbai",
      "client",
      "michelson",
      "tzip4_view"
    ],
    "successful_runs": {
      "total_time": "1951359",
      "count": "1"
    }
  },
  {
    "file": "tezt/tests/views.ml",
    "title": "Nairobi: Test view runtimes - op_toplevel_inconsistent_output_type - True",
    "tags": [
      "nairobi",
      "client",
      "michelson"
    ],
    "successful_runs": {
      "total_time": "3287721",
      "count": "1"
    }
  },
  {
    "file": "tezt/tests/views.ml",
    "title": "Mumbai: Create contract with view",
    "tags": [
      "mumbai",
      "client",
      "michelson"
    ],
    "successful_runs": {
      "total_time": "4842613",
      "count": "1"
    }
  },
  {
    "file": "tezt/tests/views.ml",
    "title": "Nairobi: self after view - self_after_fib_view",
    "tags": [
      "nairobi",
      "client",
      "michelson"
    ],
    "successful_runs": {
      "total_time": "3526163",
      "count": "1"
    }
  },
  {
    "file": "tezt/tests/views.ml",
    "title": "Alpha: sender after view - sender_after_view",
    "tags": [
      "alpha",
      "client",
      "michelson"
    ],
    "successful_runs": {
      "total_time": "2846230",
      "count": "1"
    }
  },
  {
    "file": "tezt/tests/views.ml",
    "title": "Alpha: Typecheck view - view_op_invalid_arity",
    "tags": [
      "alpha",
      "client",
      "michelson"
    ],
    "successful_runs": {
      "total_time": "1115594",
      "count": "1"
    }
  },
  {
    "file": "tezt/tests/views.ml",
    "title": "Mumbai: Typecheck view - view_op_invalid_arity",
    "tags": [
      "mumbai",
      "client",
      "michelson"
    ],
    "successful_runs": {
      "total_time": "1386803",
      "count": "1"
    }
  },
  {
    "file": "tezt/tests/zk_rollup.ml",
    "title": "Mumbai: failing_origination",
    "tags": [
      "mumbai",
      "zk_rollup"
    ],
    "successful_runs": {
      "total_time": "7521311",
      "count": "1"
    }
  },
  {
    "file": "tezt/tests/dal.ml",
    "title": "Alpha: Testing DAL node (dal attestor with baker daemon)",
    "tags": [
      "alpha",
      "dal",
      "layer1"
    ],
    "successful_runs": {
      "total_time": "42969721",
      "count": "1"
    }
  },
  {
    "file": "src/lib_scoru_wasm/regressions/tezos_scoru_wasm_regressions.ml",
    "title": "kernel link_store_create run (hash, v0)",
    "tags": [
      "regression",
      "wasm_2_0_0",
      "link_store_create",
      "hash",
      "v0"
    ],
    "successful_runs": {
      "total_time": "138417",
      "count": "1"
    }
  }
]